{
  "item_title": "derClusterForecastingResponse",
  "cache_control": "max-age=10,must-revalidate",
  "cache_expires": 10,
  "resource_methods": [
    "GET",
    "POST"
  ],
  "item_methods": [
    "GET",
    "PATCH",
    "PUT",
    "DELETE"
  ],
  "schema": {
    "date": {
      "type": "datetime",
      "required": true
    },
    "upwards_flexibility": {
      "type": "datetime",
      "required": true
    },
    "downwards_flexibility": {
      "type": "datetime",
      "required": true
    }
  }
}
